{"ongoing_trials": {"tuner0": "0002"}, "hyperparameters": {"space": [{"class_name": "Choice", "config": {"name": "units", "default": 512, "conditions": [], "values": [32, 64, 128, 256, 512], "ordered": true}}, {"class_name": "Choice", "config": {"name": "learning_rate", "default": 0.0001, "conditions": [], "values": [0.01, 0.001, 0.0001], "ordered": true}}], "values": {"units": 512, "learning_rate": 0.0001}}, "start_order": ["0000", "0001", "0002"], "end_order": ["0000", "0001"], "run_times": {"0000": 1, "0001": 1}, "retry_queue": [], "seed": 764, "seed_state": 770, "tried_so_far": ["b3e0a296aac7b81d6a15d8ea8816b7cc", "e2ed709e2a1877d54f3c16608175b647", "e29db12fd0102dee019d2efe3f43d9e0"], "id_to_hash": {"0000": "e2ed709e2a1877d54f3c16608175b647", "0001": "e29db12fd0102dee019d2efe3f43d9e0", "0002": "b3e0a296aac7b81d6a15d8ea8816b7cc"}, "display": {"search_start": "2024-03-03T05:00:24.353597", "trial_start": {"0000": "2024-03-03T05:00:24.353597", "0001": "2024-03-03T05:00:34.417371"}, "trial_number": {"0000": 1, "0001": 2}}, "hyperband_iterations": 1, "max_epochs": 10, "min_epochs": 1, "factor": 3, "brackets": [{"bracket_num": 2, "rounds": [[{"past_id": null, "id": "0000"}, {"past_id": null, "id": "0001"}, {"past_id": null, "id": "0002"}], [], []]}], "current_bracket": 2, "current_iteration": 0}